pystream_collections/__init__.py
pystream_collections/async_stream.py
pystream_collections/base.py
pystream_collections/enums.py
pystream_collections/stream.py
pystream_collections/typedef.py
pystream_collections-0.2.1.dist-info/METADATA
pystream_collections-0.2.1.dist-info/WHEEL
pystream_collections-0.2.1.dist-info/RECORD
