Metadata-Version: 2.1
Name: pystream_collections
Version: 0.2.1
Summary: A helper library to manage collections more easily
License: MIT
Author: Mariano Anaya
Author-email: mariano_anaya@yahoo.com.ar
Requires-Python: >=3.12,<4.0
Classifier: License :: OSI Approved :: MIT License
Classifier: Programming Language :: Python :: 3
Classifier: Programming Language :: Python :: 3.12
Classifier: Programming Language :: Python :: 3.13
Requires-Dist: pytest-cov (>=5,<7)
